dummy_app/__init__.py
dummy_app/app.py
dummy_app/finalized_model.sav
dummy_app/model_api_v2.py
dummy_app/test.db
dummy_app-0.0.2.dist-info/METADATA
dummy_app-0.0.2.dist-info/WHEEL
dummy_app-0.0.2.dist-info/RECORD
