Metadata-Version: 2.1
Name: dummy-app
Version: 0.0.2
Summary: My dummy dash app
Author: Lachlan Bubb
Author-email: lachlan_bubb@live.com
Requires-Python: >=3.8.18,<4.0.0
Classifier: Programming Language :: Python :: 3
Classifier: Programming Language :: Python :: 3.9
Classifier: Programming Language :: Python :: 3.10
Classifier: Programming Language :: Python :: 3.11
Classifier: Programming Language :: Python :: 3.12
Requires-Dist: Flask (==3.0.0)
Requires-Dist: SQLAlchemy (==2.0.22)
Requires-Dist: black (==23.11.0)
Requires-Dist: dash (>=2.0.0,<3.0.0)
Requires-Dist: flake8 (==6.1.0)
Requires-Dist: numpy (==1.24.4)
Requires-Dist: pandas (==2.0.3)
Requires-Dist: requests (==2.31.0)
Requires-Dist: scikit-learn (==1.3.1)
